{
  "site": {
    "name": "AZ Games by Poki2",
    "shortName": "AZ Games",
    "domain": "https://azgames.poki2.online",
    "email": "contact@poki2.online",
    "faviconUrl": "https://azgames.poki2.online/favicon.svg",
    "buildDate": "2026-04-01"
  },
  "pages": [
    {
      "slug": "index",
      "outputFile": "index.html",
      "title": "AZ Games by Poki2 — Play 300+ Free Online Games Instantly",
      "description": "Play 300+ free browser games at AZ Games by Poki2 — clicker, IO, adventure, shooting, sports, car, puzzle, casual and kids. No download, no login needed.",
      "keywords": "az games, az games free online, play games online free, unblocked games, browser games no download, free games 2026, brainrot games online, italian brainrot clicker, labubu clicker game, escape road game online, 2 player games no download",
      "canonical": "https://azgames.poki2.online/",
      "bodyClass": "home-page",
      "h1": "AZ Games by Poki2: Play 300+ Free Online Games",
      "og": {
        "title": "AZ Games by Poki2 — Play 300+ Free Online Games Instantly",
        "description": "300+ free browser games — clicker, IO, adventure, shooting, car, sports, puzzle, casual, kids. No download, no login.",
        "type": "website",
        "url": "https://azgames.poki2.online/",
        "image": "https://azgames.poki2.online/favicon.svg"
      },
      "twitter": {
        "card": "summary_large_image",
        "title": "AZ Games by Poki2 — Play 300+ Free Online Games Instantly",
        "description": "300+ free browser games — no download, no login. Instant play.",
        "image": "https://azgames.poki2.online/favicon.svg"
      },
      "changefreq": "daily",
      "priority": "1.0"
    },
    {
      "slug": "about",
      "outputFile": "about.html",
      "title": "About AZ Games by Poki2",
      "description": "Learn about AZ Games by Poki2, a free online gaming hub offering 300+ browser games across 10 categories. No downloads, no accounts — just instant fun.",
      "keywords": "about az games, free online games, browser games hub",
      "canonical": "https://azgames.poki2.online/about.html",
      "bodyClass": "about-page",
      "h1": "About AZ Games by Poki2",
      "og": {
        "title": "About AZ Games by Poki2",
        "description": "Learn about AZ Games by Poki2, a free online gaming hub offering 300+ browser games. No downloads, no accounts.",
        "type": "website",
        "url": "https://azgames.poki2.online/about.html",
        "image": "https://azgames.poki2.online/favicon.svg"
      },
      "twitter": {
        "card": "summary_large_image",
        "title": "About AZ Games by Poki2",
        "description": "Learn about AZ Games by Poki2, a free online gaming hub offering 300+ browser games.",
        "image": "https://azgames.poki2.online/favicon.svg"
      },
      "changefreq": "monthly",
      "priority": "0.6"
    },
    {
      "slug": "privacy",
      "outputFile": "privacy.html",
      "title": "Privacy Policy — AZ Games by Poki2",
      "description": "Read the AZ Games by Poki2 Privacy Policy. Learn what data we collect, how we use cookies and advertising, and how to manage your preferences.",
      "keywords": "az games privacy policy",
      "canonical": "https://azgames.poki2.online/privacy.html",
      "bodyClass": "privacy-page",
      "h1": "Privacy Policy",
      "og": {
        "title": "Privacy Policy — AZ Games by Poki2",
        "description": "Read the AZ Games by Poki2 privacy policy.",
        "type": "website",
        "url": "https://azgames.poki2.online/privacy.html",
        "image": "https://azgames.poki2.online/favicon.svg"
      },
      "twitter": {
        "card": "summary",
        "title": "Privacy Policy — AZ Games by Poki2",
        "description": "Read the AZ Games by Poki2 privacy policy.",
        "image": "https://azgames.poki2.online/favicon.svg"
      },
      "changefreq": "yearly",
      "priority": "0.3"
    },
    {
      "slug": "terms",
      "outputFile": "terms.html",
      "title": "Terms of Service — AZ Games by Poki2",
      "description": "Read the AZ Games by Poki2 Terms of Service. These terms govern your use of our free browser gaming site. By playing, you agree to these rules.",
      "keywords": "az games terms of service",
      "canonical": "https://azgames.poki2.online/terms.html",
      "bodyClass": "terms-page",
      "h1": "Terms of Service",
      "og": {
        "title": "Terms of Service — AZ Games by Poki2",
        "description": "Read the AZ Games by Poki2 terms of service.",
        "type": "website",
        "url": "https://azgames.poki2.online/terms.html",
        "image": "https://azgames.poki2.online/favicon.svg"
      },
      "twitter": {
        "card": "summary",
        "title": "Terms of Service — AZ Games by Poki2",
        "description": "Read the AZ Games by Poki2 terms of service.",
        "image": "https://azgames.poki2.online/favicon.svg"
      },
      "changefreq": "yearly",
      "priority": "0.3"
    },
    {
      "slug": "contact",
      "outputFile": "contact.html",
      "title": "Contact AZ Games by Poki2",
      "description": "Contact the AZ Games by Poki2 team. Report broken games, suggest new titles, or ask for help. We read every message and reply within 48 hours.",
      "keywords": "az games contact, contact az games",
      "canonical": "https://azgames.poki2.online/contact.html",
      "bodyClass": "contact-page",
      "h1": "Contact Us",
      "og": {
        "title": "Contact AZ Games by Poki2",
        "description": "Get in touch with the AZ Games by Poki2 team.",
        "type": "website",
        "url": "https://azgames.poki2.online/contact.html",
        "image": "https://azgames.poki2.online/favicon.svg"
      },
      "twitter": {
        "card": "summary",
        "title": "Contact AZ Games by Poki2",
        "description": "Get in touch with the AZ Games by Poki2 team.",
        "image": "https://azgames.poki2.online/favicon.svg"
      },
      "changefreq": "yearly",
      "priority": "0.5"
    }
  ]
}
